{
  "project": "bank-portal",
  "sprint": 14,
  "feature": "FEAT-012",
  "pipeline_type": "new-feature",
  "pipeline_step": "5",
  "pipeline_step_name": "code-reviewer",
  "status": "gate_pending",
  "timestamp": "2026-03-23T19:00:00Z",
  "completed_steps": ["1","2","3","3b","4","5"],
  "pending_steps": ["5b","6","7","8","9"],
  "last_skill": "code-reviewer",
  "last_artifact": "docs/code-review/CR-FEAT-012-sprint14.md",
  "gates": {
    "1": { "status": "approved", "by": "product-owner", "at": "2026-03-23T10:00:00Z" },
    "2": { "status": "approved", "by": "product-owner", "at": "2026-03-23T10:30:00Z" },
    "3": { "status": "approved", "by": "tech-lead",     "at": "2026-03-23T11:00:00Z" },
    "4": { "status": "approved", "by": "tech-lead",     "at": "2026-03-23T18:30:00Z" },
    "5": { "status": "pending",  "by": "tech-lead",     "at": null }
  },
  "version": "2.0",
  "updated_at": "2026-03-23T19:00:00Z",
  "started_at": "2026-03-23T10:00:00Z",
  "artifacts": {
    "1":  ["docs/sprints/SPRINT-014-planning.md"],
    "2":  ["docs/srs/SRS-FEAT-012.md"],
    "3":  ["docs/architecture/hld/HLD-FEAT-012.md","docs/architecture/lld/LLD-015-profile-backend.md","docs/architecture/lld/LLD-016-profile-frontend.md"],
    "4":  ["apps/backend-2fa/src/main/java/com/experis/sofia/bankportal/dashboard","apps/backend-2fa/src/main/java/com/experis/sofia/bankportal/profile","apps/backend-2fa/src/main/resources/db/migration/V14__profile_management.sql"],
    "5":  ["docs/code-review/CR-FEAT-012-sprint14.md"]
  },
  "client": "Banco Meridian",
  "sprint_goal": "Desbloquear STG (DEBT-022), saldar RV-013..017, e iniciar FEAT-012-A",
  "capacity_sp": 24,
  "velocity_reference": 23.6,
  "jira_epic": "SCRUM-35",
  "debt_resolved": ["DEBT-022","DEBT-023"],
  "rv_resolved": ["RV-013","RV-014","RV-015","RV-016","RV-017","RV-018","RV-019","RV-021","RV-022","RV-023"],
  "rv_deferred": ["RV-020"],
  "tests_total_estimated": 153,
  "resume_next": "Step 5b — Security Agent"
}
